kognitos/bdk/cli/__init__.py
kognitos/bdk/cli/commands/__init__.py
kognitos/bdk/cli/commands/describe_authentication_cmd.py
kognitos/bdk/cli/commands/describe_authentications_cmd.py
kognitos/bdk/cli/commands/describe_book_cmd.py
kognitos/bdk/cli/commands/describe_books_cmd.py
kognitos/bdk/cli/commands/describe_configurations_cmd.py
kognitos/bdk/cli/commands/describe_environment_cmd.py
kognitos/bdk/cli/commands/describe_procedure_cmd.py
kognitos/bdk/cli/commands/describe_procedures_cmd.py
kognitos/bdk/cli/commands/help_cmd.py
kognitos/bdk/cli/commands/invoke_procedure_cmd.py
kognitos/bdk/cli/commands/memory_cmd.py
kognitos/bdk/cli/commands/test_connection_cmd.py
kognitos/bdk/cli/config/__init__.py
kognitos/bdk/cli/config/config_loader.py
kognitos/bdk/cli/config/configs.py
kognitos/bdk/cli/core/__init__.py
kognitos/bdk/cli/core/bdk_runtime_client.py
kognitos/bdk/cli/core/client.py
kognitos/bdk/cli/core/memory_storage.py
kognitos/bdk/cli/main.py
kognitos/bdk/cli/ui/__init__.py
kognitos/bdk/cli/ui/authentication.py
kognitos/bdk/cli/ui/books.py
kognitos/bdk/cli/ui/common.py
kognitos/bdk/cli/ui/configs.py
kognitos/bdk/cli/ui/describe.py
kognitos/bdk/cli/ui/environment.py
kognitos/bdk/cli/ui/format.py
kognitos/bdk/cli/ui/formatters/__init__.py
kognitos/bdk/cli/ui/formatters/type.py
kognitos/bdk/cli/ui/formatters/value.py
kognitos/bdk/cli/ui/procedure.py
kognitos/bdk/cli/ui/rich_table_utils.py
kognitos/bdk/cli/utils.py
kognitos_bdk_runtime_client_cli-1.9.4.dist-info/LICENSE
kognitos_bdk_runtime_client_cli-1.9.4.dist-info/METADATA
kognitos_bdk_runtime_client_cli-1.9.4.dist-info/WHEEL
kognitos_bdk_runtime_client_cli-1.9.4.dist-info/entry_points.txt
kognitos_bdk_runtime_client_cli-1.9.4.dist-info/RECORD
